laproxy/__init__.py
laproxy/_http.py
laproxy/_laproxy.py
laproxy/_tcp.py
laproxy/py.typed
laproxy-1.1.0.dist-info/METADATA
laproxy-1.1.0.dist-info/WHEEL
laproxy-1.1.0.dist-info/RECORD
