Metadata-Version: 2.1
Name: laproxy
Version: 1.1.0
Summary: An easy to use proxy for A/D CTFs
Home-page: https://github.com/rikyiso01/LaProxy
License: MIT
Keywords: proxy,ctf-tools,attack-defense-ctf
Author: Riccardo Isola
Author-email: riky.isola@gmail.com
Requires-Python: >=3.8,<4.0
Classifier: Development Status :: 5 - Production/Stable
Classifier: Intended Audience :: Developers
Classifier: Intended Audience :: System Administrators
Classifier: License :: OSI Approved :: MIT License
Classifier: Natural Language :: English
Classifier: Operating System :: POSIX :: Linux
Classifier: Programming Language :: Python :: 3
Classifier: Programming Language :: Python :: 3.8
Classifier: Programming Language :: Python :: 3.9
Classifier: Programming Language :: Python :: 3.10
Classifier: Programming Language :: Python :: 3.11
Classifier: Topic :: Internet :: Proxy Servers
Classifier: Typing :: Typed
Requires-Dist: aiotools (>=1.6.1,<2.0.0)
Requires-Dist: attrs (>=23.1.0,<24.0.0)
Requires-Dist: typing-extensions (>=4.7.1,<5.0.0)
Project-URL: Documentation, https://rikyiso01.github.io/LaProxy
Project-URL: Repository, https://github.com/rikyiso01/LaProxy
